sisense_automl/__init__.py
sisense_automl/common_imports.py
sisense_automl/sisense_automl.py
sisense_automl-0.1.6.dist-info/LICENSE
sisense_automl-0.1.6.dist-info/METADATA
sisense_automl-0.1.6.dist-info/WHEEL
sisense_automl-0.1.6.dist-info/top_level.txt
sisense_automl-0.1.6.dist-info/RECORD
