Metadata-Version: 2.1
Name: sisense-automl
Version: 0.1.6
Summary: A package for automating machine learning processes using Sisense and AutoML.
Home-page: https://github.com/hnegi01/sisense-automl.git
Author: Himanshu Negi
Author-email: himanshu.negi.08@gmail.com
License: MIT
Classifier: Programming Language :: Python :: 3
Classifier: License :: OSI Approved :: MIT License
Classifier: Operating System :: OS Independent
Requires-Python: >=3.6
License-File: LICENSE
Requires-Dist: pandas
Requires-Dist: numpy
Requires-Dist: joblib
Requires-Dist: scikit-learn (==0.24.0)
Requires-Dist: auto-sklearn
Requires-Dist: seaborn
Requires-Dist: matplotlib
Requires-Dist: Cython
